svdi/__init__.py
svdi/cli.py
svdi/constant.py
svdi/file/__init__.py
svdi/file/format.py
svdi/main.py
svdi/svd/__init__.py
svdi/svd/basic_rSVD.py
svdi/svd/numpy_default.py
svdi/svd/pcafast.py
svdi/svd/power_iterations.py
svdi/svd/result.py
svdi-1.0.1.dist-info/LICENCE
svdi-1.0.1.dist-info/METADATA
svdi-1.0.1.dist-info/WHEEL
svdi-1.0.1.dist-info/entry_points.txt
svdi-1.0.1.dist-info/RECORD
