Metadata-Version: 2.1
Name: svdi
Version: 1.0.1
Summary: Image compression and decompression tool using SVD
License: MIT
Author: Vadim Yakshigulov
Author-email: toadharvard@gmail.com
Requires-Python: >=3.10
Classifier: License :: OSI Approved :: MIT License
Classifier: Programming Language :: Python :: 3
Classifier: Programming Language :: Python :: 3.10
Classifier: Programming Language :: Python :: 3.11
Classifier: Programming Language :: Python :: 3.12
Requires-Dist: numpy (>=1.26.4,<2.0.0)
Requires-Dist: pillow (>=10.3.0,<11.0.0)
Requires-Dist: scipy (>=1.13.0,<2.0.0)
Requires-Dist: typer[all] (>=0.12.3,<0.13.0)
